dfpipe/__init__.py
dfpipe/__main__.py
dfpipe/cli.py
dfpipe/core/__init__.py
dfpipe/core/base.py
dfpipe/core/pipeline.py
dfpipe/core/registry.py
dfpipe/loaders/__init__.py
dfpipe/loaders/csv_loader.py
dfpipe/processors/__init__.py
dfpipe/processors/base_processor.py
dfpipe/utils/__init__.py
dfpipe/utils/logging.py
dfpipe/writers/__init__.py
dfpipe/writers/csv_writer.py
dfpipe-0.0.3.dist-info/licenses/LICENSE
dfpipe-0.0.3.dist-info/METADATA
dfpipe-0.0.3.dist-info/WHEEL
dfpipe-0.0.3.dist-info/entry_points.txt
dfpipe-0.0.3.dist-info/top_level.txt
dfpipe-0.0.3.dist-info/RECORD
